banhxeo/__init__.py
banhxeo/py.typed
banhxeo/core/__init__.py
banhxeo/core/tokenizer.py
banhxeo/core/vocabulary.py
banhxeo/data/__init__.py
banhxeo/data/base.py
banhxeo/data/config.py
banhxeo/data/torch.py
banhxeo/data/transforms.py
banhxeo/data/dataset/__init__.py
banhxeo/data/dataset/amazon_review.py
banhxeo/data/dataset/imdb.py
banhxeo/model/__init__.py
banhxeo/model/base.py
banhxeo/model/config.py
banhxeo/model/head.py
banhxeo/model/neural.py
banhxeo/model/classic/__init__.py
banhxeo/model/classic/glove.py
banhxeo/model/classic/gru.py
banhxeo/model/classic/lstm.py
banhxeo/model/classic/mlp.py
banhxeo/model/classic/rnn.py
banhxeo/model/classic/word2vec.py
banhxeo/model/llm/__init__.py
banhxeo/model/llm/config.py
banhxeo/model/llm/gpt2.py
banhxeo/model/llm/layers/__init__.py
banhxeo/model/llm/layers/layer_norm.py
banhxeo/model/old/__init__.py
banhxeo/model/old/n_gram.py
banhxeo/train/__init__.py
banhxeo/train/callbacks.py
banhxeo/train/config.py
banhxeo/train/trainer.py
banhxeo/utils/__init__.py
banhxeo/utils/file.py
banhxeo/utils/logging.py
banhxeo-0.1.3.dist-info/METADATA
banhxeo-0.1.3.dist-info/WHEEL
banhxeo-0.1.3.dist-info/licenses/LICENSE
banhxeo-0.1.3.dist-info/RECORD
