Metadata-Version: 2.4
Name: banhxeo
Version: 0.1.3
Author-email: Le Nguyen <lenguyen18072003@gmail.com>
License: MIT License
License-File: LICENSE
Requires-Python: <3.13,>=3.9
Requires-Dist: asyncer>=0.0.8
Requires-Dist: datasets>=3.6.0
Requires-Dist: einops>=0.8.1
Requires-Dist: gdown>=5.2.0
Requires-Dist: jaxtyping>=0.2.36
Requires-Dist: numpy
Requires-Dist: optuna>=4.3.0
Requires-Dist: polars
Requires-Dist: pydantic>=2.11.4
Requires-Dist: torch
Requires-Dist: torchinfo>=1.8.0
Requires-Dist: tqdm
